anpp/__init__.py
anpp/template/LICENSE
anpp/template/Makefile
anpp/template/androiddir.bash
anpp/template/androiddir.bash.template
anpp/template/config.json
anpp/template/custom.sh
anpp/template/generator.py
anpp/template/tools/custom.py
anpp/template/tools/custom.sh
anpp-0.1.4.dist-info/METADATA
anpp-0.1.4.dist-info/WHEEL
anpp-0.1.4.dist-info/entry_points.txt
anpp-0.1.4.dist-info/top_level.txt
anpp-0.1.4.dist-info/RECORD
