Metadata-Version: 2.1
Name: anpp
Version: 0.1.4
Summary: Android Project Product
Home-page: https://github.com/ZengjfOS/anpp
Author: zengjf
Author-email: zengjf42@163.com
License: UNKNOWN
Project-URL: Bug Tracker, https://github.com/ZengjfOS/anpp/issues
Platform: UNKNOWN
Classifier: Programming Language :: Python :: 3
Classifier: License :: OSI Approved :: MIT License
Classifier: Operating System :: OS Independent
Requires-Python: >=3.0
